enstaller-4.8.8.dist-info/DESCRIPTION.rst
enstaller-4.8.8.dist-info/top_level.txt
enstaller-4.8.8.dist-info/WHEEL
enstaller-4.8.8.dist-info/entry_points.txt
enstaller-4.8.8.dist-info/pbr.json
enstaller-4.8.8.dist-info/RECORD
enstaller-4.8.8.dist-info/metadata.json
enstaller-4.8.8.dist-info/METADATA
egginst/main.py
egginst/links.py
egginst/testing_utils.py
egginst/utils.py
egginst/eggmeta.py
egginst/scripts.py
egginst/_win32_compat.py
egginst/object_code.py
egginst/repair_broken_egg_info.py
egginst/__init__.py
egginst/logger.py
egginst/_post_install_lib.py
egginst/progress.py
egginst/exe_data.py
egginst/errors.py
egginst/_compat.py
egginst/bootstrap.py
egginst/_zipfile.py
egginst/console/_termui_win32.py
egginst/console/_termui.py
egginst/console/__init__.py
egginst/console/simple.py
egginst/vendor/__init__.py
egginst/vendor/six.py
egginst/tests/test_links.py
egginst/tests/test_progress.py
egginst/tests/test_testing_utils.py
egginst/tests/test__zipfile.py
egginst/tests/test_utils.py
egginst/tests/test_egginst.py
egginst/tests/test_repair_egg_info.py
egginst/tests/common.py
egginst/tests/test_object_code.py
egginst/tests/__init__.py
egginst/tests/test_eggmeta.py
egginst/tests/test_scripts.py
egginst/tests/data/dummy_with_entry_points-1.0.0-1.egg
egginst/tests/data/PyYAML-3.11-py2.7-linux-x86_64.egg
egginst/tests/data/MKL-10.3-1.egg
egginst/tests/data/dummy-1.0.1-1.egg
egginst/tests/data/dummy_with_proxy-1.3.40-3.egg
egginst/tests/data/VTK-5.10.1-1.egg
egginst/tests/data/dummy_with_proxy_softlink-1.0.0-1.egg
egginst/tests/data/dummy_with_proxy_scripts-1.0.0-1.egg
egginst/tests/data/Jinja2-2.6-py2.7.egg
egginst/tests/data/nose-1.2.1-1.egg
egginst/tests/data/nose-1.3.0-2.egg
egginst/tests/data/nose-1.3.0-1.egg
egginst/tests/data/dummy_with_appinst-1.0.0-1.egg
egginst/tests/data/flake8-2.0.0-2.egg
egginst/tests/data/zip_with_softlink.zip
egginst/tests/data/macho/foo_amd64
egginst/tests/data/macho/foo_rpath.dylib
egginst/tests/data/macho/libfoo.dylib
egginst/tests/data/macho/foo.so
egginst/tests/data/macho/foo_x86
egginst/tests/data/macho/dummy_with_target_dat-1.0.0-1.egg
enstaller/main.py
enstaller/_version.py
enstaller/utils.py
enstaller/proxy_info.py
enstaller/requests_utils.py
