Metadata-Version: 2.0
Name: enstaller
Version: 4.8.8
Summary: Install and managing tool for egg-based packages
Home-page: https://github.com/enthought/enstaller
Author: Enthought, Inc.
Author-email: info@enthought.com
License: BSD
Platform: UNKNOWN
Classifier: License :: OSI Approved :: BSD License
Classifier: Development Status :: 5 - Production/Stable
Classifier: Intended Audience :: Developers
Classifier: Operating System :: OS Independent
Classifier: Programming Language :: Python :: 2.6
Classifier: Programming Language :: Python :: 2.7
Classifier: Topic :: System :: Software Distribution
Classifier: Topic :: System :: Systems Administration
